{
  "id": "array15",
  "shortName": "Array Subset Check",
  "domain": "programming",
  "category": "Array Problems",
  "difficulty": "Easy",
  "topics": [
    "Array",
    "Hash Table"
  ],
  "question": "Is Subset",
  "description": "Given two arrays `a` and `b`, determine if `b` is a subset of `a`. Every element of `b` (including duplicates) must appear in `a` with at least that frequency.\\n\\n' +\n        '**Example 1:**\\n' +\n        '```\\nInput: a = [1,2,2,3], b = [2,2]\\nOutput: true\\n```\\n\\n' +\n        '**Example 2:**\\n' +\n        '```\\nInput: a = [1,2,3], b = [2,2]\\nOutput: false\\nExplanation: a only has one 2\\n```\\n\\n' +\n        '**Constraints:**\\n' +\n        '- `0 <= a.length, b.length <= 10⁵`",
  "requirements": [
    "Time complexity: O(n + m)",
    "Use frequency map for array a"
  ],
  "hints": [
    "Build a frequency map for a.",
    "For each element in b, decrement count; if it goes negative, return false."
  ]
}